license.txt
setup.cfg
setup.py
typevalidator/__init__.py
typevalidator/numvalidator.py
typevalidator.egg-info/PKG-INFO
typevalidator.egg-info/SOURCES.txt
typevalidator.egg-info/dependency_links.txt
typevalidator.egg-info/top_level.txt