Metadata-Version: 2.1
Name: typevalidator
Version: 1.0
Summary: Returns True whenever the datatype is the object
Home-page: https://github.com/TRC-Loop/typevalidator
Download-URL: https://github.com/TRC-Loop/typevalidator/archive/refs/tags/1.0.tar.gz
Author: TRCLoop
Author-email: aro.yt.mail@gmail.com
License: MIT
Keywords: datatypes,lightweight,easy
Platform: UNKNOWN
Classifier: Development Status :: 3 - Alpha
Classifier: Intended Audience :: Developers
Classifier: Topic :: Software Development :: Build Tools
Classifier: License :: OSI Approved :: MIT License
Classifier: Programming Language :: Python :: 3
Classifier: Programming Language :: Python :: 3.4
Classifier: Programming Language :: Python :: 3.5
Classifier: Programming Language :: Python :: 3.6
License-File: license.txt
